[
    {
        "%vlocity_namespace%__DomainObjectAPIName__c": "json",
        "%vlocity_namespace%__DomainObjectCreationOrder__c": 0,
        "%vlocity_namespace%__DomainObjectFieldAPIName__c": "Claims",
        "%vlocity_namespace%__FilterGroup__c": 0,
        "%vlocity_namespace%__FilterOperator__c": "=",
        "%vlocity_namespace%__FilterValue__c": "Id",
        "%vlocity_namespace%__FormulaOrder__c": 0,
        "%vlocity_namespace%__InterfaceFieldAPIName__c": "%vlocity_namespace%__PrimaryPolicyAssetId__c",
        "%vlocity_namespace%__InterfaceObjectLookupOrder__c": 1,
        "%vlocity_namespace%__InterfaceObjectName__c": "%vlocity_namespace%__InsuranceClaim__c",
        "%vlocity_namespace%__IsDisabled__c": false,
        "%vlocity_namespace%__IsRequiredForUpsert__c": false,
        "%vlocity_namespace%__LinkCreatedIndex__c": 0,
        "%vlocity_namespace%__MapId__c": "InsGetPolicyClaimListCustoma0O3h000001bpKREAYItem0",
        "%vlocity_namespace%__OMplusSyncEnabled__c": true,
        "%vlocity_namespace%__UpsertKey__c": false,
        "Name": "InsGetPolicyClaimList",
        "VlocityDataPackType": "SObject",
        "VlocityRecordSObjectType": "%vlocity_namespace%__DRMapItem__c"
    },
    {
        "%vlocity_namespace%__DomainObjectAPIName__c": "json",
        "%vlocity_namespace%__DomainObjectCreationOrder__c": 0,
        "%vlocity_namespace%__DomainObjectFieldAPIName__c": "Claims",
        "%vlocity_namespace%__FilterGroup__c": 0,
        "%vlocity_namespace%__FilterOperator__c": "LIMIT",
        "%vlocity_namespace%__FilterValue__c": "5",
        "%vlocity_namespace%__FormulaOrder__c": 0,
        "%vlocity_namespace%__InterfaceObjectLookupOrder__c": 1,
        "%vlocity_namespace%__InterfaceObjectName__c": "%vlocity_namespace%__InsuranceClaim__c",
        "%vlocity_namespace%__IsDisabled__c": false,
        "%vlocity_namespace%__IsRequiredForUpsert__c": false,
        "%vlocity_namespace%__LinkCreatedIndex__c": 0,
        "%vlocity_namespace%__MapId__c": "InsGetPolicyClaimListCustom8757",
        "%vlocity_namespace%__OMplusSyncEnabled__c": true,
        "%vlocity_namespace%__UpsertKey__c": false,
        "Name": "InsGetPolicyClaimList",
        "VlocityDataPackType": "SObject",
        "VlocityRecordSObjectType": "%vlocity_namespace%__DRMapItem__c"
    },
    {
        "%vlocity_namespace%__DomainObjectAPIName__c": "json",
        "%vlocity_namespace%__DomainObjectCreationOrder__c": 0,
        "%vlocity_namespace%__DomainObjectFieldAPIName__c": "Claims",
        "%vlocity_namespace%__FilterGroup__c": 0,
        "%vlocity_namespace%__FilterOperator__c": "ORDER BY",
        "%vlocity_namespace%__FilterValue__c": "%vlocity_namespace%__LossDate__c DESC",
        "%vlocity_namespace%__FormulaOrder__c": 0,
        "%vlocity_namespace%__InterfaceObjectLookupOrder__c": 1,
        "%vlocity_namespace%__InterfaceObjectName__c": "%vlocity_namespace%__InsuranceClaim__c",
        "%vlocity_namespace%__IsDisabled__c": false,
        "%vlocity_namespace%__IsRequiredForUpsert__c": false,
        "%vlocity_namespace%__LinkCreatedIndex__c": 0,
        "%vlocity_namespace%__MapId__c": "InsGetPolicyClaimListCustoma0O3h000001bpKREAYItem4",
        "%vlocity_namespace%__OMplusSyncEnabled__c": true,
        "%vlocity_namespace%__UpsertKey__c": false,
        "Name": "InsGetPolicyClaimList",
        "VlocityDataPackType": "SObject",
        "VlocityRecordSObjectType": "%vlocity_namespace%__DRMapItem__c"
    },
    {
        "%vlocity_namespace%__DomainObjectAPIName__c": "json",
        "%vlocity_namespace%__DomainObjectCreationOrder__c": 0,
        "%vlocity_namespace%__DomainObjectFieldAPIName__c": "InsClaim",
        "%vlocity_namespace%__FilterGroup__c": 0,
        "%vlocity_namespace%__FilterOperator__c": "=",
        "%vlocity_namespace%__FilterValue__c": "Id",
        "%vlocity_namespace%__InterfaceFieldAPIName__c": "PolicyNumberId",
        "%vlocity_namespace%__InterfaceObjectLookupOrder__c": 2,
        "%vlocity_namespace%__InterfaceObjectName__c": "Claim",
        "%vlocity_namespace%__IsDisabled__c": false,
        "%vlocity_namespace%__IsRequiredForUpsert__c": false,
        "%vlocity_namespace%__MapId__c": "InsGetPolicyClaimListCustom4923",
        "%vlocity_namespace%__OMplusSyncEnabled__c": true,
        "%vlocity_namespace%__UpsertKey__c": false,
        "Name": "InsGetPolicyClaimList",
        "VlocityDataPackType": "SObject",
        "VlocityRecordSObjectType": "%vlocity_namespace%__DRMapItem__c"
    },
    {
        "%vlocity_namespace%__DomainObjectAPIName__c": "json",
        "%vlocity_namespace%__DomainObjectCreationOrder__c": 0,
        "%vlocity_namespace%__DomainObjectFieldAPIName__c": "InsClaim",
        "%vlocity_namespace%__FilterGroup__c": 0,
        "%vlocity_namespace%__FilterOperator__c": "LIMIT",
        "%vlocity_namespace%__FilterValue__c": "5",
        "%vlocity_namespace%__InterfaceObjectLookupOrder__c": 2,
        "%vlocity_namespace%__InterfaceObjectName__c": "Claim",
        "%vlocity_namespace%__IsDisabled__c": false,
        "%vlocity_namespace%__IsRequiredForUpsert__c": false,
        "%vlocity_namespace%__MapId__c": "InsGetPolicyClaimListCustom4729",
        "%vlocity_namespace%__OMplusSyncEnabled__c": true,
        "%vlocity_namespace%__UpsertKey__c": false,
        "Name": "InsGetPolicyClaimList",
        "VlocityDataPackType": "SObject",
        "VlocityRecordSObjectType": "%vlocity_namespace%__DRMapItem__c"
    },
    {
        "%vlocity_namespace%__DomainObjectAPIName__c": "json",
        "%vlocity_namespace%__DomainObjectCreationOrder__c": 0,
        "%vlocity_namespace%__DomainObjectFieldAPIName__c": "InsClaim",
        "%vlocity_namespace%__FilterGroup__c": 0,
        "%vlocity_namespace%__FilterOperator__c": "ORDER BY",
        "%vlocity_namespace%__FilterValue__c": "LossDate",
        "%vlocity_namespace%__InterfaceObjectLookupOrder__c": 2,
        "%vlocity_namespace%__InterfaceObjectName__c": "Claim",
        "%vlocity_namespace%__IsDisabled__c": false,
        "%vlocity_namespace%__IsRequiredForUpsert__c": false,
        "%vlocity_namespace%__MapId__c": "InsGetPolicyClaimListCustom3890",
        "%vlocity_namespace%__OMplusSyncEnabled__c": true,
        "%vlocity_namespace%__UpsertKey__c": false,
        "Name": "InsGetPolicyClaimList",
        "VlocityDataPackType": "SObject",
        "VlocityRecordSObjectType": "%vlocity_namespace%__DRMapItem__c"
    },
    {
        "%vlocity_namespace%__DomainObjectAPIName__c": "json",
        "%vlocity_namespace%__DomainObjectCreationOrder__c": 1,
        "%vlocity_namespace%__DomainObjectFieldAPIName__c": "ClaimStatus",
        "%vlocity_namespace%__FormulaOrder__c": 0,
        "%vlocity_namespace%__InterfaceFieldAPIName__c": "Claims:%vlocity_namespace%__ClaimStatus__c",
        "%vlocity_namespace%__IsDisabled__c": false,
        "%vlocity_namespace%__IsRequiredForUpsert__c": false,
        "%vlocity_namespace%__LinkCreatedIndex__c": 0,
        "%vlocity_namespace%__MapId__c": "InsGetPolicyClaimListCustoma0O3h000001bpKREAYItem12",
        "%vlocity_namespace%__OMplusSyncEnabled__c": true,
        "%vlocity_namespace%__UpsertKey__c": false,
        "Name": "InsGetPolicyClaimList",
        "VlocityDataPackType": "SObject",
        "VlocityRecordSObjectType": "%vlocity_namespace%__DRMapItem__c"
    },
    {
        "%vlocity_namespace%__DomainObjectAPIName__c": "json",
        "%vlocity_namespace%__DomainObjectCreationOrder__c": 1,
        "%vlocity_namespace%__DomainObjectFieldAPIName__c": "ClaimStatus",
        "%vlocity_namespace%__InterfaceFieldAPIName__c": "InsClaim:Status",
        "%vlocity_namespace%__IsDisabled__c": false,
        "%vlocity_namespace%__IsRequiredForUpsert__c": false,
        "%vlocity_namespace%__MapId__c": "InsGetPolicyClaimListCustom5353",
        "%vlocity_namespace%__OMplusSyncEnabled__c": true,
        "%vlocity_namespace%__UpsertKey__c": false,
        "Name": "InsGetPolicyClaimList",
        "VlocityDataPackType": "SObject",
        "VlocityRecordSObjectType": "%vlocity_namespace%__DRMapItem__c"
    },
    {
        "%vlocity_namespace%__DomainObjectAPIName__c": "json",
        "%vlocity_namespace%__DomainObjectCreationOrder__c": 1,
        "%vlocity_namespace%__DomainObjectFieldAPIName__c": "Id",
        "%vlocity_namespace%__FormulaOrder__c": 0,
        "%vlocity_namespace%__InterfaceFieldAPIName__c": "Claims:Id",
        "%vlocity_namespace%__IsDisabled__c": false,
        "%vlocity_namespace%__IsRequiredForUpsert__c": false,
        "%vlocity_namespace%__LinkCreatedIndex__c": 0,
        "%vlocity_namespace%__MapId__c": "InsGetPolicyClaimListCustoma0O3h000001bpKREAYItem15",
        "%vlocity_namespace%__OMplusSyncEnabled__c": true,
        "%vlocity_namespace%__UpsertKey__c": false,
        "Name": "InsGetPolicyClaimList",
        "VlocityDataPackType": "SObject",
        "VlocityRecordSObjectType": "%vlocity_namespace%__DRMapItem__c"
    },
    {
        "%vlocity_namespace%__DomainObjectAPIName__c": "json",
        "%vlocity_namespace%__DomainObjectCreationOrder__c": 1,
        "%vlocity_namespace%__DomainObjectFieldAPIName__c": "Id",
        "%vlocity_namespace%__InterfaceFieldAPIName__c": "InsClaim:Id",
        "%vlocity_namespace%__IsDisabled__c": false,
        "%vlocity_namespace%__IsRequiredForUpsert__c": false,
        "%vlocity_namespace%__MapId__c": "InsGetPolicyClaimListCustom7171",
        "%vlocity_namespace%__OMplusSyncEnabled__c": true,
        "%vlocity_namespace%__UpsertKey__c": false,
        "Name": "InsGetPolicyClaimList",
        "VlocityDataPackType": "SObject",
        "VlocityRecordSObjectType": "%vlocity_namespace%__DRMapItem__c"
    },
    {
        "%vlocity_namespace%__DomainObjectAPIName__c": "json",
        "%vlocity_namespace%__DomainObjectCreationOrder__c": 1,
        "%vlocity_namespace%__DomainObjectFieldAPIName__c": "LossCause",
        "%vlocity_namespace%__FormulaOrder__c": 0,
        "%vlocity_namespace%__InterfaceFieldAPIName__c": "Claims:%vlocity_namespace%__LossCause__c",
        "%vlocity_namespace%__IsDisabled__c": false,
        "%vlocity_namespace%__IsRequiredForUpsert__c": false,
        "%vlocity_namespace%__LinkCreatedIndex__c": 0,
        "%vlocity_namespace%__MapId__c": "InsGetPolicyClaimListCustoma0O3h000001bpKREAYItem20",
        "%vlocity_namespace%__OMplusSyncEnabled__c": true,
        "%vlocity_namespace%__UpsertKey__c": false,
        "Name": "InsGetPolicyClaimList",
        "VlocityDataPackType": "SObject",
        "VlocityRecordSObjectType": "%vlocity_namespace%__DRMapItem__c"
    },
    {
        "%vlocity_namespace%__DomainObjectAPIName__c": "json",
        "%vlocity_namespace%__DomainObjectCreationOrder__c": 1,
        "%vlocity_namespace%__DomainObjectFieldAPIName__c": "LossCause",
        "%vlocity_namespace%__InterfaceFieldAPIName__c": "InsClaim:ClaimReasonType",
        "%vlocity_namespace%__IsDisabled__c": false,
        "%vlocity_namespace%__IsRequiredForUpsert__c": false,
        "%vlocity_namespace%__MapId__c": "InsGetPolicyClaimListCustom525",
        "%vlocity_namespace%__OMplusSyncEnabled__c": true,
        "%vlocity_namespace%__UpsertKey__c": false,
        "Name": "InsGetPolicyClaimList",
        "VlocityDataPackType": "SObject",
        "VlocityRecordSObjectType": "%vlocity_namespace%__DRMapItem__c"
    },
    {
        "%vlocity_namespace%__DomainObjectAPIName__c": "json",
        "%vlocity_namespace%__DomainObjectCreationOrder__c": 1,
        "%vlocity_namespace%__DomainObjectFieldAPIName__c": "LossDate",
        "%vlocity_namespace%__FormulaOrder__c": 0,
        "%vlocity_namespace%__InterfaceFieldAPIName__c": "Claims:%vlocity_namespace%__LossDate__c",
        "%vlocity_namespace%__IsDisabled__c": false,
        "%vlocity_namespace%__IsRequiredForUpsert__c": false,
        "%vlocity_namespace%__LinkCreatedIndex__c": 0,
        "%vlocity_namespace%__MapId__c": "InsGetPolicyClaimListCustoma0O3h000001bpKREAYItem21",
        "%vlocity_namespace%__OMplusSyncEnabled__c": true,
        "%vlocity_namespace%__UpsertKey__c": false,
        "Name": "InsGetPolicyClaimList",
        "VlocityDataPackType": "SObject",
        "VlocityRecordSObjectType": "%vlocity_namespace%__DRMapItem__c"
    },
    {
        "%vlocity_namespace%__DomainObjectAPIName__c": "json",
        "%vlocity_namespace%__DomainObjectCreationOrder__c": 1,
        "%vlocity_namespace%__DomainObjectFieldAPIName__c": "LossDate",
        "%vlocity_namespace%__InterfaceFieldAPIName__c": "InsClaim:LossDate",
        "%vlocity_namespace%__IsDisabled__c": false,
        "%vlocity_namespace%__IsRequiredForUpsert__c": false,
        "%vlocity_namespace%__MapId__c": "InsGetPolicyClaimListCustom9687",
        "%vlocity_namespace%__OMplusSyncEnabled__c": true,
        "%vlocity_namespace%__UpsertKey__c": false,
        "Name": "InsGetPolicyClaimList",
        "VlocityDataPackType": "SObject",
        "VlocityRecordSObjectType": "%vlocity_namespace%__DRMapItem__c"
    },
    {
        "%vlocity_namespace%__DomainObjectAPIName__c": "json",
        "%vlocity_namespace%__DomainObjectCreationOrder__c": 1,
        "%vlocity_namespace%__DomainObjectFieldAPIName__c": "LossType",
        "%vlocity_namespace%__FormulaOrder__c": 0,
        "%vlocity_namespace%__InterfaceFieldAPIName__c": "Claims:%vlocity_namespace%__LossType__c",
        "%vlocity_namespace%__IsDisabled__c": false,
        "%vlocity_namespace%__IsRequiredForUpsert__c": false,
        "%vlocity_namespace%__LinkCreatedIndex__c": 0,
        "%vlocity_namespace%__MapId__c": "InsGetPolicyClaimListCustoma0O3h000001bpKREAYItem62",
        "%vlocity_namespace%__OMplusSyncEnabled__c": true,
        "%vlocity_namespace%__UpsertKey__c": false,
        "Name": "InsGetPolicyClaimList",
        "VlocityDataPackType": "SObject",
        "VlocityRecordSObjectType": "%vlocity_namespace%__DRMapItem__c"
    },
    {
        "%vlocity_namespace%__DomainObjectAPIName__c": "json",
        "%vlocity_namespace%__DomainObjectCreationOrder__c": 1,
        "%vlocity_namespace%__DomainObjectFieldAPIName__c": "LossType",
        "%vlocity_namespace%__InterfaceFieldAPIName__c": "InsClaim:ClaimType",
        "%vlocity_namespace%__IsDisabled__c": false,
        "%vlocity_namespace%__IsRequiredForUpsert__c": false,
        "%vlocity_namespace%__MapId__c": "InsGetPolicyClaimListCustom2020",
        "%vlocity_namespace%__OMplusSyncEnabled__c": true,
        "%vlocity_namespace%__UpsertKey__c": false,
        "Name": "InsGetPolicyClaimList",
        "VlocityDataPackType": "SObject",
        "VlocityRecordSObjectType": "%vlocity_namespace%__DRMapItem__c"
    },
    {
        "%vlocity_namespace%__DomainObjectAPIName__c": "json",
        "%vlocity_namespace%__DomainObjectCreationOrder__c": 1,
        "%vlocity_namespace%__DomainObjectFieldAPIName__c": "Name",
        "%vlocity_namespace%__InterfaceFieldAPIName__c": "Claims:Name",
        "%vlocity_namespace%__IsDisabled__c": false,
        "%vlocity_namespace%__IsRequiredForUpsert__c": false,
        "%vlocity_namespace%__MapId__c": "InsGetPolicyClaimListCustom6918",
        "%vlocity_namespace%__OMplusSyncEnabled__c": true,
        "%vlocity_namespace%__UpsertKey__c": false,
        "Name": "InsGetPolicyClaimList",
        "VlocityDataPackType": "SObject",
        "VlocityRecordSObjectType": "%vlocity_namespace%__DRMapItem__c"
    },
    {
        "%vlocity_namespace%__DomainObjectAPIName__c": "json",
        "%vlocity_namespace%__DomainObjectCreationOrder__c": 1,
        "%vlocity_namespace%__DomainObjectFieldAPIName__c": "Name",
        "%vlocity_namespace%__FormulaOrder__c": 0,
        "%vlocity_namespace%__InterfaceFieldAPIName__c": "InsClaim:Name",
        "%vlocity_namespace%__IsDisabled__c": false,
        "%vlocity_namespace%__IsRequiredForUpsert__c": false,
        "%vlocity_namespace%__LinkCreatedIndex__c": 0,
        "%vlocity_namespace%__MapId__c": "InsGetPolicyClaimListCustoma0O3h000001bpKREAYItem23",
        "%vlocity_namespace%__OMplusSyncEnabled__c": true,
        "%vlocity_namespace%__UpsertKey__c": false,
        "Name": "InsGetPolicyClaimList",
        "VlocityDataPackType": "SObject",
        "VlocityRecordSObjectType": "%vlocity_namespace%__DRMapItem__c"
    },
    {
        "%vlocity_namespace%__DomainObjectAPIName__c": "json",
        "%vlocity_namespace%__DomainObjectCreationOrder__c": 1,
        "%vlocity_namespace%__DomainObjectFieldAPIName__c": "ReportedDate",
        "%vlocity_namespace%__FormulaOrder__c": 0,
        "%vlocity_namespace%__InterfaceFieldAPIName__c": "Claims:%vlocity_namespace%__ReportedDate__c",
        "%vlocity_namespace%__IsDisabled__c": false,
        "%vlocity_namespace%__IsRequiredForUpsert__c": false,
        "%vlocity_namespace%__LinkCreatedIndex__c": 0,
        "%vlocity_namespace%__MapId__c": "InsGetPolicyClaimListCustoma0O3h000001bpKREAYItem40",
        "%vlocity_namespace%__OMplusSyncEnabled__c": true,
        "%vlocity_namespace%__UpsertKey__c": false,
        "Name": "InsGetPolicyClaimList",
        "VlocityDataPackType": "SObject",
        "VlocityRecordSObjectType": "%vlocity_namespace%__DRMapItem__c"
    },
    {
        "%vlocity_namespace%__DomainObjectAPIName__c": "json",
        "%vlocity_namespace%__DomainObjectCreationOrder__c": 1,
        "%vlocity_namespace%__DomainObjectFieldAPIName__c": "ReportedDate",
        "%vlocity_namespace%__InterfaceFieldAPIName__c": "InsClaim:InitiationDate",
        "%vlocity_namespace%__IsDisabled__c": false,
        "%vlocity_namespace%__IsRequiredForUpsert__c": false,
        "%vlocity_namespace%__MapId__c": "InsGetPolicyClaimListCustom9802",
        "%vlocity_namespace%__OMplusSyncEnabled__c": true,
        "%vlocity_namespace%__UpsertKey__c": false,
        "Name": "InsGetPolicyClaimList",
        "VlocityDataPackType": "SObject",
        "VlocityRecordSObjectType": "%vlocity_namespace%__DRMapItem__c"
    },
    {
        "%vlocity_namespace%__DomainObjectAPIName__c": "json",
        "%vlocity_namespace%__DomainObjectCreationOrder__c": 1,
        "%vlocity_namespace%__DomainObjectFieldAPIName__c": "StatusDate",
        "%vlocity_namespace%__FormulaOrder__c": 0,
        "%vlocity_namespace%__InterfaceFieldAPIName__c": "Claims:%vlocity_namespace%__StatusDate__c",
        "%vlocity_namespace%__IsDisabled__c": false,
        "%vlocity_namespace%__IsRequiredForUpsert__c": false,
        "%vlocity_namespace%__LinkCreatedIndex__c": 0,
        "%vlocity_namespace%__MapId__c": "InsGetPolicyClaimListCustoma0O3h000001bpKWEAYItem83",
        "%vlocity_namespace%__OMplusSyncEnabled__c": true,
        "%vlocity_namespace%__UpsertKey__c": false,
        "Name": "InsGetPolicyClaimList",
        "VlocityDataPackType": "SObject",
        "VlocityRecordSObjectType": "%vlocity_namespace%__DRMapItem__c"
    },
    {
        "%vlocity_namespace%__DomainObjectAPIName__c": "json",
        "%vlocity_namespace%__DomainObjectCreationOrder__c": 1,
        "%vlocity_namespace%__DomainObjectFieldAPIName__c": "TotalAmount",
        "%vlocity_namespace%__InterfaceFieldAPIName__c": "Claims:%vlocity_namespace%__ClaimTotalAmount__c",
        "%vlocity_namespace%__IsDisabled__c": false,
        "%vlocity_namespace%__IsRequiredForUpsert__c": false,
        "%vlocity_namespace%__MapId__c": "InsGetPolicyClaimListCustoma0O3h000001bpKWEAYItem49",
        "%vlocity_namespace%__OMplusSyncEnabled__c": true,
        "%vlocity_namespace%__UpsertKey__c": false,
        "Name": "InsGetPolicyClaimList",
        "VlocityDataPackType": "SObject",
        "VlocityRecordSObjectType": "%vlocity_namespace%__DRMapItem__c"
    },
    {
        "%vlocity_namespace%__DomainObjectAPIName__c": "json",
        "%vlocity_namespace%__DomainObjectCreationOrder__c": 1,
        "%vlocity_namespace%__DomainObjectFieldAPIName__c": "TotalAmount",
        "%vlocity_namespace%__InterfaceFieldAPIName__c": "InsClaim:ActualAmount",
        "%vlocity_namespace%__IsDisabled__c": false,
        "%vlocity_namespace%__IsRequiredForUpsert__c": false,
        "%vlocity_namespace%__MapId__c": "InsGetPolicyClaimListCustom1136",
        "%vlocity_namespace%__OMplusSyncEnabled__c": true,
        "%vlocity_namespace%__UpsertKey__c": false,
        "Name": "InsGetPolicyClaimList",
        "VlocityDataPackType": "SObject",
        "VlocityRecordSObjectType": "%vlocity_namespace%__DRMapItem__c"
    },
    {
        "%vlocity_namespace%__DomainObjectAPIName__c": "json",
        "%vlocity_namespace%__DomainObjectCreationOrder__c": 1,
        "%vlocity_namespace%__DomainObjectFieldAPIName__c": "TotalOutstanding",
        "%vlocity_namespace%__FormulaOrder__c": 0,
        "%vlocity_namespace%__InterfaceFieldAPIName__c": "Claims:%vlocity_namespace%__TotalOutstanding__c",
        "%vlocity_namespace%__IsDisabled__c": false,
        "%vlocity_namespace%__IsRequiredForUpsert__c": false,
        "%vlocity_namespace%__LinkCreatedIndex__c": 0,
        "%vlocity_namespace%__MapId__c": "InsGetPolicyClaimListCustoma0O3h000001bpKREAYItem87",
        "%vlocity_namespace%__OMplusSyncEnabled__c": true,
        "%vlocity_namespace%__UpsertKey__c": false,
        "Name": "InsGetPolicyClaimList",
        "VlocityDataPackType": "SObject",
        "VlocityRecordSObjectType": "%vlocity_namespace%__DRMapItem__c"
    },
    {
        "%vlocity_namespace%__DomainObjectAPIName__c": "json",
        "%vlocity_namespace%__DomainObjectCreationOrder__c": 1,
        "%vlocity_namespace%__DomainObjectFieldAPIName__c": "TotalPaid",
        "%vlocity_namespace%__FormulaOrder__c": 0,
        "%vlocity_namespace%__InterfaceFieldAPIName__c": "Claims:%vlocity_namespace%__TotalPaid__c",
        "%vlocity_namespace%__IsDisabled__c": false,
        "%vlocity_namespace%__IsRequiredForUpsert__c": false,
        "%vlocity_namespace%__LinkCreatedIndex__c": 0,
        "%vlocity_namespace%__MapId__c": "InsGetPolicyClaimListCustoma0O3h000001bpKREAYItem48",
        "%vlocity_namespace%__OMplusSyncEnabled__c": true,
        "%vlocity_namespace%__UpsertKey__c": false,
        "Name": "InsGetPolicyClaimList",
        "VlocityDataPackType": "SObject",
        "VlocityRecordSObjectType": "%vlocity_namespace%__DRMapItem__c"
    },
    {
        "%vlocity_namespace%__DomainObjectAPIName__c": "json",
        "%vlocity_namespace%__DomainObjectCreationOrder__c": 1,
        "%vlocity_namespace%__DomainObjectFieldAPIName__c": "TotalPaid",
        "%vlocity_namespace%__InterfaceFieldAPIName__c": "InsClaim:ApprovedAmount",
        "%vlocity_namespace%__IsDisabled__c": false,
        "%vlocity_namespace%__IsRequiredForUpsert__c": false,
        "%vlocity_namespace%__MapId__c": "InsGetPolicyClaimListCustom824",
        "%vlocity_namespace%__OMplusSyncEnabled__c": true,
        "%vlocity_namespace%__UpsertKey__c": false,
        "Name": "InsGetPolicyClaimList",
        "VlocityDataPackType": "SObject",
        "VlocityRecordSObjectType": "%vlocity_namespace%__DRMapItem__c"
    }
]